<Solution>
  <Task Id="74" MCP="0" Core="0" WCRT="848.1" />
  <Task Id="81" MCP="0" Core="0" WCRT="712.8" />
  <Task Id="71" MCP="0" Core="0" WCRT="9.9" />
  <Task Id="82" MCP="0" Core="0" WCRT="761.2" />
  <Task Id="60" MCP="0" Core="0" WCRT="388.3" />
  <Task Id="64" MCP="0" Core="0" WCRT="113.3" />
  <Task Id="92" MCP="0" Core="0" WCRT="4.4" />
  <Task Id="61" MCP="0" Core="0" WCRT="561.0" />
  <Task Id="123" MCP="0" Core="0" WCRT="52.8" />
  <Task Id="73" MCP="0" Core="0" WCRT="376.2" />
  <Task Id="68" MCP="0" Core="0" WCRT="51.7" />
  <Task Id="45" MCP="0" Core="0" WCRT="1087.9" />
  <Task Id="69" MCP="0" Core="0" WCRT="210.1" />
  <Task Id="76" MCP="0" Core="1" WCRT="42.0" />
  <Task Id="62" MCP="0" Core="1" WCRT="358.5" />
  <Task Id="39" MCP="0" Core="1" WCRT="208.5" />
  <Task Id="93" MCP="0" Core="1" WCRT="97.5" />
  <Task Id="143" MCP="0" Core="1" WCRT="2518.5" />
  <Task Id="27" MCP="0" Core="1" WCRT="331.5" />
  <Task Id="78" MCP="0" Core="2" WCRT="223.2" />
  <Task Id="38" MCP="0" Core="2" WCRT="113.4" />
  <Task Id="94" MCP="0" Core="2" WCRT="81.9" />
  <Task Id="130" MCP="0" Core="2" WCRT="5155.2" />
  <Task Id="88" MCP="0" Core="2" WCRT="93.6" />
  <Task Id="83" MCP="0" Core="2" WCRT="117.0" />
  <Task Id="41" MCP="0" Core="2" WCRT="587.7" />
  <Task Id="70" MCP="0" Core="2" WCRT="244.8" />
  <Task Id="37" MCP="0" Core="2" WCRT="53.1" />
  <Task Id="134" MCP="0" Core="2" WCRT="185.4" />
  <Task Id="80" MCP="0" Core="2" WCRT="533.7" />
  <Task Id="117" MCP="0" Core="2" WCRT="389.7" />
  <Task Id="59" MCP="0" Core="2" WCRT="219.6" />
  <Task Id="124" MCP="0" Core="2" WCRT="293.4" />
  <Task Id="79" MCP="0" Core="2" WCRT="360.0" />
  <Task Id="75" MCP="0" Core="2" WCRT="5650.2" />
  <Task Id="148" MCP="0" Core="2" WCRT="89.1" />
  <Task Id="129" MCP="0" Core="2" WCRT="2478.6" />
  <Task Id="91" MCP="0" Core="2" WCRT="202.5" />
  <Task Id="29" MCP="1" Core="0" WCRT="136.5" />
  <Task Id="107" MCP="1" Core="0" WCRT="399.1" />
  <Task Id="131" MCP="1" Core="0" WCRT="1614.6" />
  <Task Id="46" MCP="1" Core="0" WCRT="1110.2" />
  <Task Id="50" MCP="1" Core="0" WCRT="410.8" />
  <Task Id="137" MCP="1" Core="0" WCRT="3970.2" />
  <Task Id="139" MCP="1" Core="0" WCRT="1469.0" />
  <Task Id="48" MCP="1" Core="0" WCRT="339.3" />
  <Task Id="55" MCP="1" Core="0" WCRT="71.5" />
  <Task Id="77" MCP="1" Core="1" WCRT="5.4" />
  <Task Id="26" MCP="1" Core="1" WCRT="89.1" />
  <Task Id="142" MCP="1" Core="1" WCRT="722.7" />
  <Task Id="84" MCP="1" Core="1" WCRT="13.5" />
  <Task Id="44" MCP="1" Core="1" WCRT="40.5" />
  <Task Id="3" MCP="1" Core="1" WCRT="4.5" />
  <Task Id="56" MCP="1" Core="1" WCRT="404.1" />
  <Task Id="125" MCP="1" Core="1" WCRT="95.4" />
  <Task Id="51" MCP="1" Core="1" WCRT="1447.2" />
  <Task Id="103" MCP="1" Core="1" WCRT="232.2" />
  <Task Id="40" MCP="1" Core="1" WCRT="117.0" />
  <Task Id="47" MCP="1" Core="1" WCRT="2312.1" />
  <Task Id="133" MCP="1" Core="1" WCRT="2326.5" />
  <Task Id="58" MCP="1" Core="1" WCRT="281.7" />
  <Task Id="31" MCP="1" Core="1" WCRT="704.7" />
  <Task Id="43" MCP="1" Core="1" WCRT="231.3" />
  <Task Id="120" MCP="2" Core="0" WCRT="468.9" />
  <Task Id="108" MCP="2" Core="0" WCRT="68.4" />
  <Task Id="53" MCP="2" Core="0" WCRT="2118.6" />
  <Task Id="65" MCP="2" Core="0" WCRT="155.7" />
  <Task Id="35" MCP="2" Core="0" WCRT="377.1" />
  <Task Id="52" MCP="2" Core="0" WCRT="20.7" />
  <Task Id="28" MCP="2" Core="0" WCRT="90.9" />
  <Task Id="149" MCP="2" Core="0" WCRT="273.6" />
  <Task Id="49" MCP="2" Core="0" WCRT="182.7" />
  <Task Id="122" MCP="2" Core="0" WCRT="149.4" />
  <Task Id="119" MCP="2" Core="0" WCRT="594.0" />
  <Task Id="121" MCP="2" Core="0" WCRT="3575.7" />
  <Task Id="114" MCP="2" Core="0" WCRT="144.0" />
  <Task Id="90" MCP="2" Core="0" WCRT="22.5" />
  <Task Id="115" MCP="2" Core="0" WCRT="373.5" />
  <Task Id="42" MCP="2" Core="0" WCRT="94.5" />
  <Task Id="66" MCP="2" Core="0" WCRT="267.3" />
  <Task Id="102" MCP="2" Core="0" WCRT="133.2" />
  <Task Id="86" MCP="2" Core="1" WCRT="804.0" />
  <Task Id="85" MCP="2" Core="1" WCRT="154.8" />
  <Task Id="87" MCP="2" Core="1" WCRT="632.4" />
  <Task Id="109" MCP="2" Core="1" WCRT="1566.0" />
  <Task Id="96" MCP="2" Core="1" WCRT="105.6" />
  <Task Id="72" MCP="2" Core="1" WCRT="156.0" />
  <Task Id="34" MCP="2" Core="1" WCRT="69.6" />
  <Task Id="89" MCP="2" Core="1" WCRT="109.2" />
  <Task Id="100" MCP="2" Core="1" WCRT="24.0" />
  <Task Id="105" MCP="2" Core="1" WCRT="5156.4" />
  <Task Id="118" MCP="2" Core="1" WCRT="200.4" />
  <Task Id="144" MCP="2" Core="1" WCRT="6006.0" />
  <Task Id="63" MCP="2" Core="1" WCRT="862.8" />
  <Task Id="67" MCP="2" Core="2" WCRT="356.4" />
  <Task Id="110" MCP="2" Core="2" WCRT="377.3" />
  <Task Id="95" MCP="2" Core="2" WCRT="18.7" />
  <Task Id="97" MCP="2" Core="2" WCRT="947.1" />
  <Task Id="146" MCP="2" Core="2" WCRT="583.0" />
  <Task Id="54" MCP="2" Core="2" WCRT="902.0" />
  <Task Id="113" MCP="2" Core="2" WCRT="95.7" />
  <Task Id="106" MCP="2" Core="2" WCRT="732.6" />
  <Task Id="128" MCP="2" Core="2" WCRT="454.3" />
  <Task Id="36" MCP="2" Core="2" WCRT="23.1" />
  <Task Id="57" MCP="2" Core="2" WCRT="7.7" />
  <Task Id="147" MCP="2" Core="2" WCRT="2458.5" />
  <Task Id="104" MCP="2" Core="2" WCRT="1579.6" />
  <Task Id="112" MCP="2" Core="2" WCRT="15469.3" />
  <Task Id="132" MCP="2" Core="2" WCRT="9802.1" />
  <Task Id="140" MCP="2" Core="2" WCRT="18377.7" />
  <Task Id="30" MCP="2" Core="2" WCRT="4220.7" />
  <Task Id="99" MCP="2" Core="3" WCRT="3.6" />
  <Task Id="150" MCP="2" Core="3" WCRT="3965.4" />
  <Task Id="32" MCP="2" Core="3" WCRT="835.2" />
  <Task Id="136" MCP="2" Core="3" WCRT="69.3" />
  <Task Id="101" MCP="2" Core="3" WCRT="109.8" />
  <Task Id="138" MCP="2" Core="3" WCRT="374.4" />
  <Task Id="33" MCP="2" Core="3" WCRT="1485.0" />
  <Task Id="127" MCP="2" Core="3" WCRT="224.1" />
  <Task Id="135" MCP="2" Core="3" WCRT="2895.3" />
  <Task Id="145" MCP="2" Core="3" WCRT="1638.0" />
  <Task Id="116" MCP="2" Core="3" WCRT="2028.6" />
  <Task Id="98" MCP="2" Core="3" WCRT="6.3" />
  <Task Id="141" MCP="2" Core="3" WCRT="10309.5" />
</Solution>
<!-- Total Laxity: 3307088.1999999997 -->